flask_requests_logging/__init__.py
flask_requests_logging-1.1.dist-info/LICENSE
flask_requests_logging-1.1.dist-info/METADATA
flask_requests_logging-1.1.dist-info/WHEEL
flask_requests_logging-1.1.dist-info/top_level.txt
flask_requests_logging-1.1.dist-info/zip-safe
flask_requests_logging-1.1.dist-info/RECORD
