Metadata-Version: 2.1
Name: flask-requests-logging
Version: 1.1
Summary: Log all your Flask requests with severity depending on the result code
Home-page: https://github.com/smok-serwis/flask-requests-logging
Author: Piotr Maślanka
Author-email: pmaslanka@smok.co
Project-URL: Code, https://github.com/smok-serwis/flask-requests-logging
Project-URL: Issue tracker, https://github.com/smok-serwis/flask-requests-logging/issues
Keywords: flask,logging,web
Classifier: Programming Language :: Python
Classifier: Programming Language :: Python :: 3.6
Classifier: Programming Language :: Python :: 3.7
Classifier: Programming Language :: Python :: 3.8
Classifier: Programming Language :: Python :: 3.9
Classifier: Programming Language :: Python :: 3.10
Classifier: Programming Language :: Python :: 3.11
Classifier: Programming Language :: Python :: Implementation :: CPython
Classifier: Programming Language :: Python :: Implementation :: PyPy
Classifier: Operating System :: POSIX
Classifier: Operating System :: OS Independent
Classifier: Development Status :: 5 - Production/Stable
Classifier: License :: OSI Approved :: MIT License
Classifier: Topic :: Software Development :: Libraries
Requires-Python: !=2.7.*,!=3.0.*,!=3.1.*,!=3.2.*,!=3.3.*,!=3.4.*,!=3.5.*
License-File: LICENSE
Requires-Dist: flask==3.*
Requires-Dist: satella>=2.26.6
